{
  "display_name": "Wise Magician",
  "fightable": false,
  "spawn": {
    "x": 13,
    "y": 7
  },
  "source_img": "./assets/entity/npc/magician/rotations/south.png",
"dialogue": {
    "init": {
      "text": "你終於醒了……我們召喚你，是因為你是唯一能對抗魔王的人，我們已收集兩個靈魂碎片，\n若不消滅魔王，碎片的力量將持續帶來災厄。",
      "options": [
        {
          "text": "我明白了，我會對抗魔王。",
          "next": "1"
        }
      ]
    },
    "1": {
      "text": "你是被封印在異界的最終武器，這是最後的賭注，也是世界唯一的生路。",
      "options": [
        {
          "text": "靈魂碎片是什麼？",
          "next": "2"
        }
      ]
    },
    "2": {
      "text": "靈魂碎片是魔王力量的來源，我們已經收集了兩個，但還有更多散落在世界各地。只有消滅魔王，才能阻止災厄繼續蔓延。",
      "options": [
        {
          "text": "我需要更多資訊。",
          "next": "3"
        }
      ]
    },
    "3": {
      "text": "你被封印在異界已經很久了，我們用盡所有力量才將你召喚回來。現在，只有你能拯救這個世界。",
      "options": [
        {
          "text": "我會不負眾望，完成使命。",
          "next": null
        },
        {
          "text": "我明白了，我會找到所有碎片並消滅魔王。",
          "next": null
        }
      ]
    }
  }
}